taskrun/__init__.py
taskrun/cluster_task.py
taskrun/common_instantiations.py
taskrun/condition.py
taskrun/counter_resource.py
taskrun/cpu_time_resource.py
taskrun/failure_mode.py
taskrun/file_cleanup_observer.py
taskrun/file_hash_condition.py
taskrun/file_hash_database.py
taskrun/file_modification_condition.py
taskrun/function_condition.py
taskrun/function_task.py
taskrun/memory_resource.py
taskrun/nop_task.py
taskrun/observer.py
taskrun/process_task.py
taskrun/resource.py
taskrun/resource_manager.py
taskrun/task.py
taskrun/task_manager.py
taskrun/verbose_observer.py
taskrun-4.2.3.dist-info/LICENSE
taskrun-4.2.3.dist-info/METADATA
taskrun-4.2.3.dist-info/NOTICE
taskrun-4.2.3.dist-info/WHEEL
taskrun-4.2.3.dist-info/top_level.txt
taskrun-4.2.3.dist-info/RECORD
